pyformatter/__init__.py
pyformatter/config.py
pyformatter/utils.py
pyformatter/cli/__init__.py
pyformatter/cli/pycommentfmt_main.py
pyformatter/cli/pydocfmt_main.py
pyformatter/formatters/__init__.py
pyformatter/formatters/google_docstrings.py
pyformatter/formatters/pycommentfmt.py
pyformatter/formatters/pydocfmt.py
python_doc_formatter-0.1.1.dist-info/licenses/LICENSE
python_doc_formatter-0.1.1.dist-info/METADATA
python_doc_formatter-0.1.1.dist-info/WHEEL
python_doc_formatter-0.1.1.dist-info/entry_points.txt
python_doc_formatter-0.1.1.dist-info/top_level.txt
python_doc_formatter-0.1.1.dist-info/RECORD
