Metadata-Version: 2.4
Name: python-doc-formatter
Version: 0.1.1
Summary: A Python annotation formatter for line-wrapping and formatting python comments and docstrings
Author-email: Rik Ghosh <rikghosh487@gmail.com>
Maintainer-email: Rik Ghosh <rikghosh487@gmail.com>
License: MIT
Project-URL: Homepage, https://github.com/RikGhosh487/pyformatter
Project-URL: Repository, https://github.com/RikGhosh487/pyformatter
Project-URL: Issues, https://github.com/RikGhosh487/pyformatter/issues
Project-URL: Changelog, https://github.com/RikGhosh487/pyformatter/blob/main/CHANGELOG.md
Project-URL: Contributing, https://github.com/RikGhosh487/pyformatter/blob/main/CONTRIBUTING.md
Project-URL: Security, https://github.com/RikGhosh487/pyformatter/blob/main/SECURITY.md
Keywords: formatter,docstring,comment,python,code-quality,linting
Classifier: Development Status :: 4 - Beta
Classifier: Environment :: Console
Classifier: Intended Audience :: Developers
Classifier: Operating System :: OS Independent
Classifier: Programming Language :: Python
Classifier: Programming Language :: Python :: 3
Classifier: Programming Language :: Python :: 3.11
Classifier: Programming Language :: Python :: 3.12
Classifier: Programming Language :: Python :: 3.13
Classifier: Programming Language :: Python :: 3 :: Only
Classifier: Topic :: Software Development :: Code Generators
Classifier: Topic :: Software Development :: Libraries :: Python Modules
Classifier: Topic :: Software Development :: Quality Assurance
Classifier: Topic :: Utilities
Requires-Python: >=3.11
License-File: LICENSE
Provides-Extra: dev
Requires-Dist: pytest>=7.0; extra == "dev"
Requires-Dist: pytest-cov>=4.0; extra == "dev"
Requires-Dist: black>=23.0; extra == "dev"
Requires-Dist: isort>=5.0; extra == "dev"
Requires-Dist: mypy>=1.0; extra == "dev"
Requires-Dist: pre-commit>=3.0; extra == "dev"
Provides-Extra: test
Requires-Dist: pytest>=7.0; extra == "test"
Requires-Dist: pytest-cov>=4.0; extra == "test"
Dynamic: license-file
